LICENSE
MANIFEST.in
README.md
setup.py
NepalStockTracker/Assets.py
NepalStockTracker/DashBoard.py
NepalStockTracker/ForgotPassword.py
NepalStockTracker/Include.py
NepalStockTracker/LoginUI.py
NepalStockTracker/NewPasswordUI.py
NepalStockTracker/PasswordConditions.py
NepalStockTracker/PlayErrorAudio.py
NepalStockTracker/Search.py
NepalStockTracker/SecurityQuestionUI.py
NepalStockTracker/SignUpUI.py
NepalStockTracker/_ComboBox.py
NepalStockTracker/_Entry.py
NepalStockTracker/_Login.py
NepalStockTracker/__init__.py
NepalStockTracker/db.py
NepalStockTracker/exceptions.py
NepalStockTracker/main.py
NepalStockTracker.egg-info/PKG-INFO
NepalStockTracker.egg-info/SOURCES.txt
NepalStockTracker.egg-info/dependency_links.txt
NepalStockTracker.egg-info/requires.txt
NepalStockTracker.egg-info/top_level.txt
NepalStockTracker/assets/1.png
NepalStockTracker/assets/Add.png
NepalStockTracker/assets/Back.png
NepalStockTracker/assets/Company Details.png
NepalStockTracker/assets/Confirm.png
NepalStockTracker/assets/DashBoard Frame.png
NepalStockTracker/assets/Delete.png
NepalStockTracker/assets/Forgot Password Frame.png
NepalStockTracker/assets/Hide Password.png
NepalStockTracker/assets/LinuxErrSound.wav
NepalStockTracker/assets/Login Frame.png
NepalStockTracker/assets/Login.png
NepalStockTracker/assets/Logout.png
NepalStockTracker/assets/Reset.png
NepalStockTracker/assets/Show Password.png
NepalStockTracker/assets/Signup Frame.png
NepalStockTracker/assets/Submit.png
NepalStockTracker/assets/Tick.png
NepalStockTracker/assets/Title Image.png
NepalStockTracker/assets/WinErrSound.wav
NepalStockTracker/assets/icon.ico
NepalStockTracker/assets/icon.png