Metadata-Version: 2.1
Name: NepalStockTracker
Version: 0.4.0
Summary: Gets the market details of the provided company. Only for Nepal's stock market
Home-page: https://github.com/ghanteyyy/NepalStockTracker.git
Author: ghanteyyy
Author-email: ghanteyyy@gmail.com
License: MIT
Classifier: Programming Language :: Python :: 3
Classifier: License :: OSI Approved :: MIT License
Classifier: Operating System :: OS Independent
Requires-Python: >=3
License-File: LICENSE
